setup.py
trac_mattermost/__init__.py
trac_mattermost/base.py
trac_mattermost/ticket_notifications.py
trac_mattermost/wiki_notifications.py
trac_mattermost.egg-info/PKG-INFO
trac_mattermost.egg-info/SOURCES.txt
trac_mattermost.egg-info/dependency_links.txt
trac_mattermost.egg-info/entry_points.txt
trac_mattermost.egg-info/requires.txt
trac_mattermost.egg-info/top_level.txt