Metadata-Version: 1.1
Name: trac-mattermost
Version: 0.1
Summary: Trac notifications in Mattermost
Home-page: http://github.com/truveris/trac-mattermost
Author: Truveris Inc.
Author-email: engineering@truveris.com
License: ISC License
Platform: UNKNOWN
Classifier: License :: OSI Approved :: ISC License (ISCL)
Classifier: Operating System :: Unix
Classifier: Programming Language :: Python
Classifier: Framework :: Trac
Classifier: Topic :: Software Development :: Bug Tracking
